tidepool_data_science_project/__init__.py
tidepool_data_science_project/util.py
tidepool_data_science_project/makedata/__init__.py
tidepool_data_science_project/makedata/make_user.py
tidepool_data_science_project/makedata/tidepool_api.py
tidepool_data_science_project/models/__init__.py
tidepool_data_science_project/models/tidepool_user_model.py
tidepool_data_science_project/visualization/__init__.py
tidepool_data_science_project/visualization/visualize_user_data.py
tidepool_data_science_project-0.0.3.dist-info/LICENSE
tidepool_data_science_project-0.0.3.dist-info/METADATA
tidepool_data_science_project-0.0.3.dist-info/WHEEL
tidepool_data_science_project-0.0.3.dist-info/top_level.txt
tidepool_data_science_project-0.0.3.dist-info/RECORD
