Metadata-Version: 2.1
Name: tidepool-data-science-project
Version: 0.0.3
Summary: Python repository to facilitate using the Tidepool API (forked). 
Home-page: https://github.com/miriamkw/data-science-tidepool-api-python
Author: Your Name
Author-email: YourName@tidepool.org
Classifier: Programming Language :: Python :: 3
Classifier: License :: OSI Approved :: BSD License
Classifier: Operating System :: OS Independent
Requires-Python: >=3.6
License-File: LICENSE
